<annotation>
	<folder>train</folder>
	<filename>Y164.JPG</filename>
	<path>/home/naseer/Documents/dataset/train/Y164.JPG</path>
	<source>
		<database>Unknown</database>
	</source>
	<size>
		<width>264</width>
		<height>336</height>
		<depth>1</depth>
	</size>
	<segmented>0</segmented>
	<object>
		<name>tumor</name>
		<pose>Unspecified</pose>
		<truncated>0</truncated>
		<difficult>0</difficult>
		<bndbox>
			<xmin>100</xmin>
			<ymin>25</ymin>
			<xmax>182</xmax>
			<ymax>103</ymax>
		</bndbox>
	</object>
</annotation>
