<annotation>
	<folder>train</folder>
	<filename>Y183.jpg</filename>
	<path>/home/naseer/Documents/dataset/train/Y183.jpg</path>
	<source>
		<database>Unknown</database>
	</source>
	<size>
		<width>300</width>
		<height>347</height>
		<depth>1</depth>
	</size>
	<segmented>0</segmented>
	<object>
		<name>tumor</name>
		<pose>Unspecified</pose>
		<truncated>0</truncated>
		<difficult>0</difficult>
		<bndbox>
			<xmin>172</xmin>
			<ymin>172</ymin>
			<xmax>254</xmax>
			<ymax>266</ymax>
		</bndbox>
	</object>
</annotation>
